hacker_news_email_sender/__init__.py
hacker_news_email_sender/__main__.py
hacker_news_email_sender/newsExctractor.py
hacker_news_email_sender-1.0.0.dist-info/LICENSE
hacker_news_email_sender-1.0.0.dist-info/METADATA
hacker_news_email_sender-1.0.0.dist-info/WHEEL
hacker_news_email_sender-1.0.0.dist-info/entry_points.txt
hacker_news_email_sender-1.0.0.dist-info/top_level.txt
hacker_news_email_sender-1.0.0.dist-info/RECORD
